gaspare/__init__.py
gaspare/_modidx.py
gaspare/client.py
gaspare/core.py
gaspare/toolloop.py
gaspare/utils.py
gaspare-0.1.3.dist-info/LICENSE
gaspare-0.1.3.dist-info/METADATA
gaspare-0.1.3.dist-info/WHEEL
gaspare-0.1.3.dist-info/entry_points.txt
gaspare-0.1.3.dist-info/top_level.txt
gaspare-0.1.3.dist-info/RECORD
