Metadata-Version: 2.1
Name: gaspare
Version: 0.1.3
Summary: A rewriting of Answer.AI's Gaspard to the new Genai SDK
Home-page: https://github.com/mikonapoli/gaspare
Author: mikonapoli
Author-email: michelangelo.bucci@gmail.com
License: Apache Software License 2.0
Keywords: nbdev jupyter notebook python gemini
Classifier: Development Status :: 4 - Beta
Classifier: Intended Audience :: Developers
Classifier: Natural Language :: English
Classifier: Programming Language :: Python :: 3.11
Classifier: Programming Language :: Python :: 3.12
Classifier: License :: OSI Approved :: Apache Software License
Requires-Python: >=3.11
License-File: LICENSE
Requires-Dist: fastcore
Requires-Dist: pillow
Requires-Dist: google-genai
Requires-Dist: toolslm
Provides-Extra: dev
